alex_test.pyd
alex_test-0.3.1.dist-info/DESCRIPTION.rst
alex_test-0.3.1.dist-info/METADATA
alex_test-0.3.1.dist-info/RECORD
alex_test-0.3.1.dist-info/WHEEL
alex_test-0.3.1.dist-info/metadata.json
alex_test-0.3.1.dist-info/top_level.txt
