Metadata-Version: 2.0
Name: alex-test
Version: 0.3.1
Summary: This is a demo package
Home-page: https://nepenthe.me/alex_demo
Author: Alexander Templeton
Author-email: blakmatr@gmail.com
License: UNKNOWN
Platform: UNKNOWN
